purposely/__init__.py
purposely/cli.py
purposely/core/__init__.py
purposely/core/creator.py
purposely/core/initializer.py
purposely/core/renderer.py
purposely/core/upgrader.py
purposely/i18n/en.json
purposely/i18n/ko.json
purposely/templates/.claude/instructions.md
purposely/templates/.claude/commands/purposely-design.md
purposely/templates/.claude/commands/purposely-implement.md
purposely/templates/.claude/commands/purposely-init.md
purposely/templates/.claude/commands/purposely-phase.md
purposely/templates/.claude/commands/purposely-plan.md
purposely/templates/.claude/commands/purposely-research.md
purposely/templates/.claude/snippets/environment-detection.md
purposely/templates/.claude/snippets/project-rules.md
purposely/templates/.claude/snippets/scripts-structure.md
purposely/templates/source/00_SPEC.md
purposely/templates/source/01_RESEARCH.md
purposely/templates/source/01_RESEARCH_OVERVIEW.md
purposely/templates/source/02_DESIGN_OVERVIEW.md
purposely/templates/source/03_PLAN.md
purposely/templates/source/04_IMPLEMENTATION.md
purposely/templates/source/0X_DESIGN_DETAIL.md
purposely/templates/source/GLOBAL_PURPOSE.md
purposely/templates/source/RULES.md
purposely-0.2.2.dist-info/entry_points.txt
purposely-0.2.2.dist-info/licenses/LICENSE
purposely-0.2.2.dist-info/WHEEL
purposely-0.2.2.dist-info/METADATA
purposely-0.2.2.dist-info/RECORD
