Metadata-Version: 2.4
Name: purposely
Version: 0.2.2
Summary: Purpose-Driven Development Framework - A CLI tool for maintaining project purpose throughout development
Keywords: cli,development,documentation,purpose-driven,template
Author: Nicered
Requires-Python: >=3.10
Classifier: Development Status :: 4 - Beta
Classifier: Intended Audience :: Developers
Classifier: License :: OSI Approved :: Apache Software License
Classifier: Programming Language :: Python :: 3
Classifier: Programming Language :: Python :: 3.10
Classifier: Programming Language :: Python :: 3.11
Classifier: Programming Language :: Python :: 3.12
Classifier: Topic :: Software Development :: Documentation
Classifier: Topic :: Software Development :: Libraries :: Python Modules
License-File: LICENSE
Requires-Dist: click>=8.1.0
Requires-Dist: jinja2>=3.1.0
Requires-Dist: pytest>=7.0.0 ; extra == "dev"
Requires-Dist: pytest-cov>=4.0.0 ; extra == "dev"
Project-URL: Documentation, https://github.com/purposely/purposely#readme
Project-URL: Homepage, https://github.com/purposely/purposely
Project-URL: Repository, https://github.com/purposely/purposely
Provides-Extra: dev
